paypal_rest/__init__.py
paypal_rest/client.py
paypal_rest/cliquery.py
paypal_rest/cliutil.py
paypal_rest/config.py
paypal_rest/errors.py
paypal_rest/paypal_types.py
paypal_rest/py.typed
paypal_rest/transaction.py
paypal_rest-1.0.4.dist-info/LICENSE.txt
paypal_rest-1.0.4.dist-info/METADATA
paypal_rest-1.0.4.dist-info/WHEEL
paypal_rest-1.0.4.dist-info/entry_points.txt
paypal_rest-1.0.4.dist-info/top_level.txt
paypal_rest-1.0.4.dist-info/RECORD
