Metadata-Version: 2.1
Name: paypal-rest
Version: 1.0.4
Summary: Library to access PayPal’s REST API
Home-page: https://k.sfconservancy.org/NPO-Accounting/paypal_rest
Author: Software Freedom Conservancy
Author-email: info@sfconservancy.org
License: GNU AGPLv3+
Project-URL: Documentation, https://k.sfconservancy.org/NPO-Accounting/paypal_rest
Project-URL: Source, https://k.sfconservancy.org/NPO-Accounting/paypal_rest
Platform: UNKNOWN
Requires-Python: >=3.6
Requires-Dist: iso8601 (>=0.1)
Requires-Dist: oauthlib (>=2.0)
Requires-Dist: pyxdg (>=0.2)
Requires-Dist: PyYAML (>=3.0)
Requires-Dist: requests (>=2.0)
Requires-Dist: requests-oauthlib (>=1.0)
